llama_cpp_guidance/__init__.py
llama_cpp_guidance/llm.py
llama_cpp_guidance-0.1.2.dist-info/METADATA
llama_cpp_guidance-0.1.2.dist-info/WHEEL
llama_cpp_guidance-0.1.2.dist-info/RECORD
