Metadata-Version: 2.1
Name: llama-cpp-guidance
Version: 0.1.2
Summary: A guidance compatibility layer for llama-cpp-python
Author: Nicholas Yager
Author-email: yager@nicholasyager.com
Requires-Python: >=3.9,<3.12
Classifier: Programming Language :: Python :: 3
Classifier: Programming Language :: Python :: 3.9
Classifier: Programming Language :: Python :: 3.10
Classifier: Programming Language :: Python :: 3.11
Requires-Dist: guidance (>=0.0.64,<0.0.65)
Requires-Dist: llama_cpp_python (>=0.1.83)
Requires-Dist: loguru (>=0.7.1,<0.8.0)
